<!DOCTYPE pof-config SYSTEM "pof-config.dtd">
<pof-config>
   <user-type-list>
    <!-- include all "standard" Coherence POF user types -->
    <include>coherence-pof-config.xml</include>
     <user-type>
       <type-id>1163</type-id>
       <class-name>oracle.toplinkgrid.codesample.pof.models.trader.Attorney</class-name>
     </user-type>
     <user-type>
       <type-id>1162</type-id>
       <class-name>oracle.toplinkgrid.codesample.pof.models.trader.Call</class-name>
     </user-type>
     <user-type>
       <type-id>1158</type-id>
       <class-name>oracle.toplinkgrid.codesample.pof.models.trader.Contact</class-name>
     </user-type>
     <user-type>
       <type-id>1157</type-id>
       <class-name>oracle.toplinkgrid.codesample.pof.models.trader.QualificationId</class-name>
     </user-type>
     <user-type>
       <type-id>1153</type-id>
       <class-name>oracle.toplinkgrid.codesample.pof.models.trader.Ask</class-name>
     </user-type>
     <user-type>
       <type-id>1152</type-id>
       <class-name>oracle.toplinkgrid.codesample.pof.models.trader.Bid</class-name>
     </user-type>
     <user-type>
       <type-id>1151</type-id>
       <class-name>oracle.toplinkgrid.codesample.pof.models.trader.Broker</class-name>
     </user-type>
     <user-type>
       <type-id>1148</type-id>
       <class-name>oracle.toplinkgrid.codesample.pof.models.trader.Qualification</class-name>
     </user-type>
     <user-type>
       <type-id>1146</type-id>
       <class-name>oracle.toplinkgrid.codesample.pof.models.trader.Security</class-name>
     </user-type>
     <user-type>
       <type-id>1145</type-id>
       <class-name>oracle.toplinkgrid.codesample.pof.models.trader.Trade</class-name>
     </user-type>
     <user-type>
       <type-id>1143</type-id>
       <class-name>oracle.toplinkgrid.codesample.pof.models.trader.Brokerage</class-name>
     </user-type>
     <user-type>
       <type-id>1144</type-id>
       <class-name>oracle.eclipselink.coherence.integrated.internal.cache.WrapperInternal</class-name>
       <serializer>
         <class-name>oracle.eclipselink.coherence.integrated.cache.WrapperPofSerializer</class-name>
       </serializer>
     </user-type>
     <user-type>
       <type-id>1142</type-id>
       <class-name>oracle.eclipselink.coherence.integrated.internal.querying.EclipseLinkExtractor</class-name>
       <serializer>
         <class-name>oracle.eclipselink.coherence.integrated.cache.ExtractorSerializer</class-name>
       </serializer>
     </user-type>
     <user-type>
       <type-id>1141</type-id>
       <class-name>oracle.eclipselink.coherence.integrated.internal.cache.VersionPutProcessor</class-name>
     </user-type>
     <user-type>
       <type-id>1140</type-id>
       <class-name>oracle.eclipselink.coherence.integrated.internal.cache.VersionRemoveProcessor</class-name>
     </user-type>
     <user-type>
       <type-id>1139</type-id>
       <class-name>oracle.eclipselink.coherence.integrated.internal.cache.RelationshipUpdateProcessor</class-name>
     </user-type>
     <user-type>
       <type-id>1138</type-id>
       <class-name>oracle.eclipselink.coherence.integrated.internal.querying.EclipseLinkFilterFactory$SubClassOf</class-name>
     </user-type>

   </user-type-list>

   <allow-interfaces>true</allow-interfaces>
   <allow-subclasses>true</allow-subclasses>
 </pof-config>

